app_module/__init__.py
app_module/app_module.py
api_k-0.1.0.dist-info/METADATA
api_k-0.1.0.dist-info/WHEEL
api_k-0.1.0.dist-info/top_level.txt
api_k-0.1.0.dist-info/RECORD
