Metadata-Version: 2.4
Name: api_k
Version: 0.1.0
Summary: A simple Flask API to manage items
Author: Baskar
Author-email: newtonbaskar@example.com
Classifier: Programming Language :: Python :: 3
Classifier: License :: OSI Approved :: MIT License
Classifier: Operating System :: OS Independent
Requires-Python: >=3.6
Requires-Dist: Flask
Dynamic: author
Dynamic: author-email
Dynamic: classifier
Dynamic: requires-dist
Dynamic: requires-python
Dynamic: summary
